<?xml version="1.0" encoding="utf-8"?>
<Document>
  <Engineering version="V21" />
  <SW.Blocks.InstanceDB ID="0">
    <AttributeList>
      <InstanceOfName>Trafiklys</InstanceOfName>
      <InstanceOfType>FB</InstanceOfType>
      <Interface>
        <Sections xmlns="http://www.siemens.com/automation/Openness/SW/Interface/v5">
          <Section Name="Input">
            <Member Name="i_start" Datatype="Bool" />
            <Member Name="i_suspendResume" Datatype="Bool" />
            <Member Name="i_manualMode" Datatype="Bool" />
            <Member Name="i_pushButtonEmergencyStop" Datatype="Bool" />
            <Member Name="i_manualRed" Datatype="Bool" />
            <Member Name="i_manualYellow" Datatype="Bool" />
            <Member Name="i_manualGreen" Datatype="Bool" />
          </Section>
          <Section Name="Output">
            <Member Name="o_red" Datatype="Bool" />
            <Member Name="o_yellow" Datatype="Bool" />
            <Member Name="o_green" Datatype="Bool" />
          </Section>
          <Section Name="InOut" />
          <Section Name="Static">
            <Member Name="statG0_step" Datatype="Array[100..102] of Bool" />
            <Member Name="statG1_step" Datatype="Array[0..4] of Bool" />
            <Member Name="statG2_step" Datatype="Array[200..201] of Bool" />
            <Member Name="statG3_step" Datatype="Array[300..301] of Bool" />
            <Member Name="statGManual" Datatype="Array[5..5] of Bool" />
            <Member Name="statSuspendResumeTrigger" Datatype="R_TRIG" Version="1.0" />
            <Member Name="statTime" Datatype="Time">
              <AttributeList>
                <BooleanAttribute Name="SetPoint" SystemDefined="true">true</BooleanAttribute>
              </AttributeList>
            </Member>
            <Member Name="statTimer_G1_step" Datatype="Array[1..4] of IEC_TIMER" Version="1.0" />
          </Section>
        </Sections>
      </Interface>
      <Name>Trafiklys_DB</Name>
      <Namespace />
      <Number>3</Number>
      <ProgrammingLanguage>DB</ProgrammingLanguage>
    </AttributeList>
    <ObjectList>
      <MultilingualText ID="1" CompositionName="Comment">
        <ObjectList>
          <MultilingualTextItem ID="2" CompositionName="Items">
            <AttributeList>
              <Culture>en-US</Culture>
              <Text />
            </AttributeList>
          </MultilingualTextItem>
        </ObjectList>
      </MultilingualText>
      <MultilingualText ID="3" CompositionName="Title">
        <ObjectList>
          <MultilingualTextItem ID="4" CompositionName="Items">
            <AttributeList>
              <Culture>en-US</Culture>
              <Text />
            </AttributeList>
          </MultilingualTextItem>
        </ObjectList>
      </MultilingualText>
    </ObjectList>
  </SW.Blocks.InstanceDB>
</Document>